verilog/test_bench_sa_single_0.v


module test_bench_sa_single_0
(

);

  reg clk;
  reg rst;
  reg start;
  wire done;

  sa_single_16cells
  sa_single_16cells
  (
    .clk(clk),
    .rst(rst),
    .start(start),
    .done(done)
  );


  initial begin
    clk = 0;
    rst = 1;
    start = 0;
  end


  initial begin
    $dumpfile("/home/jeronimo/Documentos/GIT/sa_multi/verilog/test_bench_sa_single_0.vcd");
    $dumpvars(0);
  end


  initial begin
    @(posedge clk);
    @(posedge clk);
    @(posedge clk);
    rst = 0;
    start = 1;
    #1000;
    $finish;
  end

  always #5clk=~clk;

  always @(posedge clk) begin
    if(done) begin
      $display("ACC DONE!");
      $finish;
    end 
  end


  //Simulation sector - End

endmodule



module sa_single_16cells
(
  input clk,
  input rst,
  input start,
  input done
);

  // SA single thread states declaration
  reg [4-1:0] fsm_sa;
  localparam SELECT_CELLS = 4'd0;
  localparam CELL_TO_NODES = 4'd1;
  localparam NEIGHBORHOOD = 4'd2;
  localparam NODES_TO_CELL = 4'd3;
  localparam DISTANCE_CALCULATOR = 4'd4;
  localparam SUM_REDUCTION = 4'd5;
  localparam DECISION = 4'd6;
  localparam CHANGES = 4'd7;
  localparam END = 4'd8;
  // #####

  // counter cells stage variables
  reg [4-1:0] ca;
  reg [4-1:0] cb;
  // #####
  // SA single thread FSM

  always @(posedge clk) begin
    if(rst) begin
      ca <= 4'd0;
      cb <= 4'd0;
      fsm_sa <= CELL_TO_NODES;
    end else begin
      if(start) begin
        case(fsm_sa)
          SELECT_CELLS: begin
            if(ca == 4) begin
              ca <= 4'd0;
              if(cb == 4) begin
                cb <= 4'd0;
                fsm_sa <= END;
              end else begin
                cb <= cb + 4'd1;
                fsm_sa <= CELL_TO_NODES;
              end
            end else begin
              ca <= ca + 4'd1;
              fsm_sa <= CELL_TO_NODES;
            end
          end
          CELL_TO_NODES: begin
            fsm_sa <= SELECT_CELLS;
          end
          NEIGHBORHOOD: begin
            fsm_sa <= NODES_TO_CELL;
          end
          NODES_TO_CELL: begin
            fsm_sa <= DISTANCE_CALCULATOR;
          end
          DISTANCE_CALCULATOR: begin
            fsm_sa <= SUM_REDUCTION;
          end
          SUM_REDUCTION: begin
            fsm_sa <= DECISION;
          end
          DECISION: begin
            fsm_sa <= CHANGES;
            fsm_sa <= SELECT_CELLS;
          end
          CHANGES: begin
            fsm_sa <= SELECT_CELLS;
          end
          END: begin
            fsm_sa <= END;
          end
        endcase
      end 
    end
  end


  initial begin
    fsm_sa = 0;
    ca = 0;
    cb = 0;
  end


endmodule

verilog/test_bench_sa_single_0.vcd
$date
	Fri Jan  5 12:57:05 2024
$end
$version
	Icarus Verilog
$end
$timescale
	1s
$end
$scope module test_bench_sa_single_0 $end
$var wire 1 ! done $end
$var reg 1 " clk $end
$var reg 1 # rst $end
$var reg 1 $ start $end
$scope module sa_single_16cells $end
$var wire 1 " clk $end
$var wire 1 ! done $end
$var wire 1 # rst $end
$var wire 1 $ start $end
$var parameter 4 % CELL_TO_NODES $end
$var parameter 4 & CHANGES $end
$var parameter 4 ' DECISION $end
$var parameter 4 ( DISTANCE_CALCULATOR $end
$var parameter 4 ) END $end
$var parameter 4 * NEIGHBORHOOD $end
$var parameter 4 + NODES_TO_CELL $end
$var parameter 4 , SELECT_CELLS $end
$var parameter 4 - SUM_REDUCTION $end
$var reg 4 . ca [3:0] $end
$var reg 4 / cb [3:0] $end
$var reg 4 0 fsm_sa [3:0] $end
$upscope $end
$upscope $end
$enddefinitions $end
$comment Show the parameter values. $end
$dumpall
b101 -
b0 ,
b11 +
b10 *
b1000 )
b100 (
b110 '
b111 &
b1 %
$end
#0
$dumpvars
b0 0
b0 /
b0 .
0$
1#
0"
z!
$end
#5
b1 0
1"
#10
0"
#15
1"
#20
0"
#25
b0 0
1$
0#
1"
#30
0"
#35
b1 0
b1 .
1"
#40
0"
#45
b0 0
1"
#50
0"
#55
b1 0
b10 .
1"
#60
0"
#65
b0 0
1"
#70
0"
#75
b1 0
b11 .
1"
#80
0"
#85
b0 0
1"
#90
0"
#95
b1 0
b100 .
1"
#100
0"
#105
b0 0
1"
#110
0"
#115
b1 0
b1 /
b0 .
1"
#120
0"
#125
b0 0
1"
#130
0"
#135
b1 0
b1 .
1"
#140
0"
#145
b0 0
1"
#150
0"
#155
b1 0
b10 .
1"
#160
0"
#165
b0 0
1"
#170
0"
#175
b1 0
b11 .
1"
#180
0"
#185
b0 0
1"
#190
0"
#195
b1 0
b100 .
1"
#200
0"
#205
b0 0
1"
#210
0"
#215
b1 0
b10 /
b0 .
1"
#220
0"
#225
b0 0
1"
#230
0"
#235
b1 0
b1 .
1"
#240
0"
#245
b0 0
1"
#250
0"
#255
b1 0
b10 .
1"
#260
0"
#265
b0 0
1"
#270
0"
#275
b1 0
b11 .
1"
#280
0"
#285
b0 0
1"
#290
0"
#295
b1 0
b100 .
1"
#300
0"
#305
b0 0
1"
#310
0"
#315
b1 0
b11 /
b0 .
1"
#320
0"
#325
b0 0
1"
#330
0"
#335
b1 0
b1 .
1"
#340
0"
#345
b0 0
1"
#350
0"
#355
b1 0
b10 .
1"
#360
0"
#365
b0 0
1"
#370
0"
#375
b1 0
b11 .
1"
#380
0"
#385
b0 0
1"
#390
0"
#395
b1 0
b100 .
1"
#400
0"
#405
b0 0
1"
#410
0"
#415
b1 0
b100 /
b0 .
1"
#420
0"
#425
b0 0
1"
#430
0"
#435
b1 0
b1 .
1"
#440
0"
#445
b0 0
1"
#450
0"
#455
b1 0
b10 .
1"
#460
0"
#465
b0 0
1"
#470
0"
#475
b1 0
b11 .
1"
#480
0"
#485
b0 0
1"
#490
0"
#495
b1 0
b100 .
1"
#500
0"
#505
b0 0
1"
#510
0"
#515
b1000 0
b0 /
b0 .
1"
