verilog/test_bench_sa_single_0.v


module test_bench_sa_single_0
(

);

  reg clk;
  reg rst;
  reg start;
  wire done;

  sa_single_16cells
  sa_single_16cells
  (
    .clk(clk),
    .rst(rst),
    .start(start),
    .done(done)
  );


  initial begin
    clk = 0;
    rst = 1;
    start = 0;
  end


  initial begin
    $dumpfile("/home/jeronimo/Documentos/GIT/sa_multi/verilog/test_bench_sa_single_0.vcd");
    $dumpvars(0);
  end


  initial begin
    @(posedge clk);
    @(posedge clk);
    @(posedge clk);
    rst = 0;
    start = 1;
    #1000;
    $finish;
  end

  always #5clk=~clk;

  always @(posedge clk) begin
    if(done) begin
      $display("ACC DONE!");
      $finish;
    end 
  end


  //Simulation sector - End

endmodule



module sa_single_16cells
(
  input clk,
  input rst,
  input start,
  input done
);

  // SA single thread states declaration
  reg [4-1:0] fsm_sa;
  localparam SELECT_CELLS = 4'd0;
  localparam CELL_TO_NODES = 4'd1;
  localparam NEIGHBORHOOD = 4'd2;
  localparam NODES_TO_CELL = 4'd3;
  localparam DISTANCE_CALCULATOR = 4'd4;
  localparam SUM_REDUCTION = 4'd5;
  localparam DECISION = 4'd6;
  localparam CHANGES = 4'd7;
  localparam END = 4'd8;
  // #####

  // select cells stage variables
  reg [4-1:0] ca;
  reg [4-1:0] cb;
  // #####

  // cell to nodes stage variables
  reg [4-1:0] na;
  reg na_v;
  reg [4-1:0] nb;
  reg nb_v;
  wire [4-1:0] na_t;
  wire na_v_t;
  wire [4-1:0] nb_t;
  wire nb_v_t;
  // #####

  // neighborhood stage variables
  reg [16-1:0] va;
  reg [4-1:0] va_v;
  reg [16-1:0] vb;
  reg [4-1:0] vb_v;
  wire [16-1:0] va_t;
  wire [4-1:0] va_v_t;
  wire [4-1:0] va_v_m;
  wire [16-1:0] vb_t;
  wire [4-1:0] vb_v_t;
  wire [4-1:0] vb_v_m;

  //here we guarantee that only valid nodes can give neighbors 
  assign va_v_t = (na_v)? va_v_m : 4'b0;
  assign vb_v_t = (nb_v)? vb_v_m : 4'b0;
  // #####

  // node to cell stage variables
  reg [4-1:0] cva_v;
  reg [16-1:0] cva;
  reg [4-1:0] cvb_v;
  reg [16-1:0] cvb;
  wire [4-1:0] cva_v_t;
  wire [16-1:0] cva_t;
  wire [4-1:0] cvb_v_t;
  wire [16-1:0] cvb_t;

  // This is only for legibility
  // #####
  assign cva_v_t = va_v;
  assign cvb_v_t = vb_v;

  // SA single thread FSM

  always @(posedge clk) begin
    if(rst) begin
      ca <= 4'd0;
      cb <= 4'd0;
      na <= 4'd0;
      na_v <= 1'd0;
      nb <= 4'd0;
      nb_v <= 1'd0;
      va <= 16'd0;
      va_v <= 4'd0;
      vb <= 16'd0;
      vb_v <= 4'd0;
      fsm_sa <= CELL_TO_NODES;
    end else begin
      if(start) begin
        case(fsm_sa)
          SELECT_CELLS: begin
            if(ca == 4) begin
              ca <= 4'd0;
              if(cb == 4) begin
                cb <= 4'd0;
                fsm_sa <= END;
              end else begin
                cb <= cb + 4'd1;
                fsm_sa <= CELL_TO_NODES;
              end
            end else begin
              ca <= ca + 4'd1;
              fsm_sa <= CELL_TO_NODES;
            end
          end
          CELL_TO_NODES: begin
            if(&{ ~na_v_t, ~nb_v_t }) begin
              fsm_sa <= SELECT_CELLS;
            end else begin
              na <= na_t;
              na_v <= na_v_t;
              nb <= nb_t;
              nb_v <= nb_v_t;
              fsm_sa <= NEIGHBORHOOD;
            end
          end
          NEIGHBORHOOD: begin
            va <= va_t;
            va_v <= va_v_t;
            vb <= vb_t;
            vb_v <= vb_v_t;
            fsm_sa <= NODES_TO_CELL;
          end
          NODES_TO_CELL: begin
            cva_v <= cva_v_t;
            cva <= cva_t;
            cvb_v <= cvb_v_t;
            cvb <= cvb;
            fsm_sa <= DISTANCE_CALCULATOR;
          end
          DISTANCE_CALCULATOR: begin
            fsm_sa <= SELECT_CELLS;
          end
          SUM_REDUCTION: begin
            fsm_sa <= DECISION;
          end
          DECISION: begin
            fsm_sa <= CHANGES;
            fsm_sa <= SELECT_CELLS;
          end
          CHANGES: begin
            fsm_sa <= SELECT_CELLS;
          end
          END: begin
            fsm_sa <= END;
          end
        endcase
      end 
    end
  end

  // cell to nodes stage memory instantiation

  mem_2r_1w_width5_depth4
  #(
    .READ_F(1),
    .INIT_FILE("/home/jeronimo/Documentos/GIT/sa_multi/verilog/test_bench_sa_single_0_c_n.rom"),
    .WRITE_F(1),
    .OUTPUT_FILE("/home/jeronimo/Documentos/GIT/sa_multi/verilog/test_bench_sa_single_0_c_n_out.rom")
  )
  mem_2r_1w_width5_depth4
  (
    .clk(clk),
    .rd(1'd1),
    .rd_addr0(ca),
    .rd_addr1(cb),
    .out0({ na_v_t, na_t }),
    .out1({ nb_v_t, nb_t }),
    .wr(1'd0),
    .wr_addr(4'd0),
    .wr_data(5'd0)
  );

  // #####

  // neighborhood stage memory instantiation

  mem_2r_1w_width5_depth4
  #(
    .READ_F(1),
    .INIT_FILE("/home/jeronimo/Documentos/GIT/sa_multi/verilog/test_bench_sa_single_0_n0.rom"),
    .WRITE_F(0)
  )
  mem_2r_1w_width5_depth4_0
  (
    .clk(clk),
    .rd_addr0(na),
    .rd_addr1(nb),
    .out0({ va_v_m[0], va_t[3:0] }),
    .out1({ vb_v_m[0], vb_t[3:0] }),
    .wr(1'd0),
    .wr_addr(4'd0),
    .wr_data(5'd0)
  );


  mem_2r_1w_width5_depth4
  #(
    .READ_F(1),
    .INIT_FILE("/home/jeronimo/Documentos/GIT/sa_multi/verilog/test_bench_sa_single_0_n1.rom"),
    .WRITE_F(0)
  )
  mem_2r_1w_width5_depth4_1
  (
    .clk(clk),
    .rd_addr0(na),
    .rd_addr1(nb),
    .out0({ va_v_m[1], va_t[7:4] }),
    .out1({ vb_v_m[1], vb_t[7:4] }),
    .wr(1'd0),
    .wr_addr(4'd0),
    .wr_data(5'd0)
  );


  mem_2r_1w_width5_depth4
  #(
    .READ_F(1),
    .INIT_FILE("/home/jeronimo/Documentos/GIT/sa_multi/verilog/test_bench_sa_single_0_n2.rom"),
    .WRITE_F(0)
  )
  mem_2r_1w_width5_depth4_2
  (
    .clk(clk),
    .rd_addr0(na),
    .rd_addr1(nb),
    .out0({ va_v_m[2], va_t[11:8] }),
    .out1({ vb_v_m[2], vb_t[11:8] }),
    .wr(1'd0),
    .wr_addr(4'd0),
    .wr_data(5'd0)
  );


  mem_2r_1w_width5_depth4
  #(
    .READ_F(1),
    .INIT_FILE("/home/jeronimo/Documentos/GIT/sa_multi/verilog/test_bench_sa_single_0_n3.rom"),
    .WRITE_F(0)
  )
  mem_2r_1w_width5_depth4_3
  (
    .clk(clk),
    .rd_addr0(na),
    .rd_addr1(nb),
    .out0({ va_v_m[3], va_t[15:12] }),
    .out1({ vb_v_m[3], vb_t[15:12] }),
    .wr(1'd0),
    .wr_addr(4'd0),
    .wr_data(5'd0)
  );

  // #####

  // node to cell stage memory instantiation
  // #####

  initial begin
    fsm_sa = 0;
    ca = 0;
    cb = 0;
    na = 0;
    na_v = 0;
    nb = 0;
    nb_v = 0;
    va = 0;
    va_v = 0;
    vb = 0;
    vb_v = 0;
    cva_v = 0;
    cva = 0;
    cvb_v = 0;
    cvb = 0;
  end


endmodule



module mem_2r_1w_width5_depth4 #
(
  parameter READ_F = 0,
  parameter INIT_FILE = "mem_file.txt",
  parameter WRITE_F = 0,
  parameter OUTPUT_FILE = "mem_out_file.txt"
)
(
  input clk,
  input rd,
  input [4-1:0] rd_addr0,
  input [4-1:0] rd_addr1,
  output [5-1:0] out0,
  output [5-1:0] out1,
  input wr,
  input [4-1:0] wr_addr,
  input [5-1:0] wr_data
);

  reg [5-1:0] mem [0:2**4-1];
  assign out0 = (rd)? mem[rd_addr0] : 5'd0;
  assign out1 = (rd)? mem[rd_addr1] : 5'd0;

  always @(posedge clk) begin
    if(wr) begin
      mem[wr_addr] <= wr_data;
    end 
  end

  //synthesis translate_off

  always @(posedge clk) begin
    if(wr && WRITE_F) begin
      $writememb(OUTPUT_FILE, mem);
    end 
  end

  //synthesis translate_on

  initial begin
    if(READ_F) begin
      $readmemb(INIT_FILE, mem);
    end 
  end


endmodule

verilog/test_bench_sa_single_0.vcd
$date
	Fri Jan  5 15:58:15 2024
$end
$version
	Icarus Verilog
$end
$timescale
	1s
$end
$scope module test_bench_sa_single_0 $end
$var wire 1 ! done $end
$var reg 1 " clk $end
$var reg 1 # rst $end
$var reg 1 $ start $end
$scope module sa_single_16cells $end
$var wire 1 " clk $end
$var wire 1 ! done $end
$var wire 1 # rst $end
$var wire 1 $ start $end
$var wire 1 % nb_v_t $end
$var wire 4 & nb_t [3:0] $end
$var wire 1 ' na_v_t $end
$var wire 4 ( na_t [3:0] $end
$var parameter 4 ) CELL_TO_NODES $end
$var parameter 4 * CHANGES $end
$var parameter 4 + DECISION $end
$var parameter 4 , DISTANCE_CALCULATOR $end
$var parameter 4 - END $end
$var parameter 4 . NEIGHBORHOOD $end
$var parameter 4 / NODES_TO_CELL $end
$var parameter 4 0 SELECT_CELLS $end
$var parameter 4 1 SUM_REDUCTION $end
$var reg 4 2 ca [3:0] $end
$var reg 4 3 cb [3:0] $end
$var reg 4 4 fsm_sa [3:0] $end
$var reg 4 5 na [3:0] $end
$var reg 1 6 na_v $end
$var reg 4 7 nb [3:0] $end
$var reg 1 8 nb_v $end
$scope module mem_2r_1w_width5_depth4 $end
$var wire 1 " clk $end
$var wire 5 9 out0 [4:0] $end
$var wire 5 : out1 [4:0] $end
$var wire 1 ; rd $end
$var wire 4 < rd_addr0 [3:0] $end
$var wire 4 = rd_addr1 [3:0] $end
$var wire 1 > wr $end
$var wire 4 ? wr_addr [3:0] $end
$var wire 5 @ wr_data [4:0] $end
$var parameter 616 A INIT_FILE $end
$var parameter 648 B OUTPUT_FILE $end
$var parameter 32 C READ_F $end
$var parameter 32 D WRITE_F $end
$upscope $end
$upscope $end
$upscope $end
$enddefinitions $end
$comment Show the parameter values. $end
$dumpall
b1 D
b1 C
b1011110110100001101111011011010110010100101111011010100110010101110010011011110110111001101001011011010110111100101111010001000110111101100011011101010110110101100101011011100111010001101111011100110010111101000111010010010101010000101111011100110110000101011111011011010111010101101100011101000110100100101111011101100110010101110010011010010110110001101111011001110010111101110100011001010111001101110100010111110110001001100101011011100110001101101000010111110111001101100001010111110111001101101001011011100110011101101100011001010101111100110000010111110110001101011111011011100101111101101111011101010111010000101110011100100110111101101101 B
b10111101101000011011110110110101100101001011110110101001100101011100100110111101101110011010010110110101101111001011110100010001101111011000110111010101101101011001010110111001110100011011110111001100101111010001110100100101010100001011110111001101100001010111110110110101110101011011000111010001101001001011110111011001100101011100100110100101101100011011110110011100101111011101000110010101110011011101000101111101100010011001010110111001100011011010000101111101110011011000010101111101110011011010010110111001100111011011000110010101011111001100000101111101100011010111110110111000101110011100100110111101101101 A
b101 1
b0 0
b11 /
b10 .
b1000 -
b100 ,
b110 +
b111 *
b1 )
$end
#0
$dumpvars
b0 @
b0 ?
0>
b0 =
b0 <
1;
b0 :
b0 9
08
b0 7
06
b0 5
b0 4
b0 3
b0 2
b0 (
0'
b0 &
0%
0$
1#
0"
z!
$end
#5
b1 4
1"
#10
0"
#15
1"
#20
0"
#25
b0 4
1$
0#
1"
#30
0"
#35
b1 (
1'
b1 4
b10001 9
b1 2
b1 <
1"
#40
0"
#45
b10 4
16
b1 5
1"
#50
0"
#55
b0 4
1"
#60
0"
#65
b0 (
0'
b1 4
b0 9
b10 2
b10 <
1"
#70
0"
#75
b0 4
1"
#80
0"
#85
b111 (
1'
b1 4
b10111 9
b11 2
b11 <
1"
#90
0"
#95
b10 4
b111 5
1"
#100
0"
#105
b0 4
1"
#110
0"
#115
b0 (
b1 4
b10000 9
b100 2
b100 <
1"
#120
0"
#125
b10 4
b0 5
1"
#130
0"
#135
b0 4
1"
#140
0"
#145
b1 &
1%
0'
b1 4
b10001 :
b1 3
b1 =
b0 9
b0 2
b0 <
1"
#150
0"
#155
b10 4
18
b1 7
06
1"
#160
0"
#165
b0 4
1"
#170
0"
#175
b1 (
1'
b1 4
b10001 9
b1 2
b1 <
1"
#180
0"
#185
b10 4
16
b1 5
1"
#190
0"
#195
b0 4
1"
#200
0"
#205
b0 (
0'
b1 4
b0 9
b10 2
b10 <
1"
#210
0"
#215
b10 4
06
b0 5
1"
#220
0"
#225
b0 4
1"
#230
0"
#235
b111 (
1'
b1 4
b10111 9
b11 2
b11 <
1"
#240
0"
#245
b10 4
16
b111 5
1"
#250
0"
#255
b0 4
1"
#260
0"
#265
b0 (
b1 4
b10000 9
b100 2
b100 <
1"
#270
0"
#275
b10 4
b0 5
1"
#280
0"
#285
b0 4
1"
#290
0"
#295
b0 &
0%
0'
b1 4
b0 :
b10 3
b10 =
b0 9
b0 2
b0 <
1"
#300
0"
#305
b0 4
1"
#310
0"
#315
b1 (
1'
b1 4
b10001 9
b1 2
b1 <
1"
#320
0"
#325
b10 4
08
b0 7
b1 5
1"
#330
0"
#335
b0 4
1"
#340
0"
#345
b0 (
0'
b1 4
b0 9
b10 2
b10 <
1"
#350
0"
#355
b0 4
1"
#360
0"
#365
b111 (
1'
b1 4
b10111 9
b11 2
b11 <
1"
#370
0"
#375
b10 4
b111 5
1"
#380
0"
#385
b0 4
1"
#390
0"
#395
b0 (
b1 4
b10000 9
b100 2
b100 <
1"
#400
0"
#405
b10 4
b0 5
1"
#410
0"
#415
b0 4
1"
#420
0"
#425
b111 &
1%
0'
b1 4
b10111 :
b11 3
b11 =
b0 9
b0 2
b0 <
1"
#430
0"
#435
b10 4
18
b111 7
06
1"
#440
0"
#445
b0 4
1"
#450
0"
#455
b1 (
1'
b1 4
b10001 9
b1 2
b1 <
1"
#460
0"
#465
b10 4
16
b1 5
1"
#470
0"
#475
b0 4
1"
#480
0"
#485
b0 (
0'
b1 4
b0 9
b10 2
b10 <
1"
#490
0"
#495
b10 4
06
b0 5
1"
#500
0"
#505
b0 4
1"
#510
0"
#515
b111 (
1'
b1 4
b10111 9
b11 2
b11 <
1"
#520
0"
#525
b10 4
16
b111 5
1"
#530
0"
#535
b0 4
1"
#540
0"
#545
b0 (
b1 4
b10000 9
b100 2
b100 <
1"
#550
0"
#555
b10 4
b0 5
1"
#560
0"
#565
b0 4
1"
#570
0"
#575
b0 &
0'
b1 4
b10000 :
b100 3
b100 =
b0 9
b0 2
b0 <
1"
#580
0"
#585
b10 4
b0 7
06
1"
#590
0"
#595
b0 4
1"
#600
0"
#605
b1 (
1'
b1 4
b10001 9
b1 2
b1 <
1"
#610
0"
#615
b10 4
16
b1 5
1"
#620
0"
#625
b0 4
1"
#630
0"
#635
b0 (
0'
b1 4
b0 9
b10 2
b10 <
1"
#640
0"
#645
b10 4
06
b0 5
1"
#650
0"
#655
b0 4
1"
#660
0"
#665
b111 (
1'
b1 4
b10111 9
b11 2
b11 <
1"
#670
0"
#675
b10 4
16
b111 5
1"
#680
0"
#685
b0 4
1"
#690
0"
#695
b0 (
b1 4
b10000 9
b100 2
b100 <
1"
#700
0"
#705
b10 4
b0 5
1"
#710
0"
#715
b0 4
1"
#720
0"
#725
0%
0'
b1000 4
b0 :
b0 3
b0 =
b0 9
b0 2
b0 <
1"
